README.md
setup.py
ljvillarrealm_dsnd_probability/Binomialdistribution.py
ljvillarrealm_dsnd_probability/Gaussiandistribution.py
ljvillarrealm_dsnd_probability/Generaldistribution.py
ljvillarrealm_dsnd_probability/__init__.py
ljvillarrealm_dsnd_probability.egg-info/PKG-INFO
ljvillarrealm_dsnd_probability.egg-info/SOURCES.txt
ljvillarrealm_dsnd_probability.egg-info/dependency_links.txt
ljvillarrealm_dsnd_probability.egg-info/not-zip-safe
ljvillarrealm_dsnd_probability.egg-info/top_level.txt