Metadata-Version: 1.0
Name: ljvillarrealm-dsnd-probability
Version: 0.1
Summary: Gaussian & Binomial distributions
Home-page: UNKNOWN
Author: ljvillarrealm
Author-email: ljvillarrealm@fastmail.com
License: UNKNOWN
Platform: UNKNOWN
